rara_subject_indexer/__init__.py
rara_subject_indexer/config.py
rara_subject_indexer/exceptions.py
rara_subject_indexer/rara_indexer.py
rara_subject_indexer/indexers/__init__.py
rara_subject_indexer/indexers/keyword_indexers/base_keyword_indexer.py
rara_subject_indexer/indexers/keyword_indexers/indexers.py
rara_subject_indexer/indexers/model_indexers/base_indexer.py
rara_subject_indexer/indexers/model_indexers/omikuji_indexer.py
rara_subject_indexer/indexers/model_indexers/rakun_indexer.py
rara_subject_indexer/ner/ner_keyword.py
rara_subject_indexer/ner/ner_result.py
rara_subject_indexer/ner/ner_subject_indexer.py
rara_subject_indexer/ner/ner_taggers/base_ner_tagger.py
rara_subject_indexer/ner/ner_taggers/gliner_tagger.py
rara_subject_indexer/ner/ner_taggers/stanza_ner_tagger.py
rara_subject_indexer/resources/__init__.py
rara_subject_indexer/resources/model_checksums/gdrive_checksums.json
rara_subject_indexer/resources/model_checksums/gliner_checksums.json
rara_subject_indexer/resources/model_checksums/stanza_checksums.json
rara_subject_indexer/resources/phrasers/__init__.py
rara_subject_indexer/resources/phrasers/phraser_ise_digar_et.model
rara_subject_indexer/resources/spellcheck/__init__.py
rara_subject_indexer/resources/spellcheck/en.txt
rara_subject_indexer/resources/spellcheck/et_lemmas.txt
rara_subject_indexer/resources/stopwords/__init__.py
rara_subject_indexer/resources/stopwords/en_stopwords.txt
rara_subject_indexer/resources/stopwords/et_stopwords.txt
rara_subject_indexer/resources/stopwords/et_stopwords_lemmas.txt
rara_subject_indexer/supervised/__init__.py
rara_subject_indexer/supervised/omikuji/data_loader.py
rara_subject_indexer/supervised/omikuji/feature_extractor.py
rara_subject_indexer/supervised/omikuji/label_binarizer.py
rara_subject_indexer/supervised/omikuji/omikuji_helpers.py
rara_subject_indexer/supervised/omikuji/omikuji_model.py
rara_subject_indexer/unsupervised/__init__.py
rara_subject_indexer/unsupervised/rakun/rakun_keyword_extractor.py
rara_subject_indexer-3.0.33.dist-info/licenses/LICENSE
rara_subject_indexer-3.0.33.dist-info/METADATA
rara_subject_indexer-3.0.33.dist-info/WHEEL
rara_subject_indexer-3.0.33.dist-info/top_level.txt
rara_subject_indexer-3.0.33.dist-info/RECORD
