Metadata-Version: 2.4
Name: rara-subject-indexer
Version: 3.0.33
Summary: Automatically detect subject indices.
License:                     GNU AFFERO GENERAL PUBLIC LICENSE
Classifier: Programming Language :: Python :: 3
Classifier: Programming Language :: Python :: 3.10
Classifier: Programming Language :: Python :: 3.11
Classifier: Programming Language :: Python :: 3.12
Classifier: Intended Audience :: Science/Research
Requires-Python: >=3.10
License-File: LICENSE
Requires-Dist: omikuji>=0.5.1
Requires-Dist: scikit-learn>=1.6.0
Requires-Dist: scipy>=1.13.0
Requires-Dist: estnltk==1.7.3
Requires-Dist: langdetect>=1.0.9
Requires-Dist: tqdm>=4.67
Requires-Dist: gensim>=4.3.3
Requires-Dist: nltk>=3.9.1
Requires-Dist: rakun2>=0.29
Requires-Dist: symspellpy>=6.7.8
Requires-Dist: numpy>=1.26.4
Requires-Dist: gdown>=5.2.0
Requires-Dist: gliner==0.2.*
Requires-Dist: jellyfish==1.1.*
Requires-Dist: regex==2024.11.*
Requires-Dist: stanza==1.10.*
Requires-Dist: urllib3==2.3.*
Provides-Extra: testing
Requires-Dist: pytest>=8.0; extra == "testing"
Requires-Dist: pytest-order; extra == "testing"
Dynamic: license-file
